pypykko/__init__.py
pypykko/aux-abbreviations.tsv
pypykko/aux-emoticons.tsv
pypykko/aux-units.tsv
pypykko/constants.py
pypykko/extras.py
pypykko/fi-generator.kfst
pypykko/fi-parser.kfst
pypykko/file_tools.py
pypykko/generate.py
pypykko/normalize.py
pypykko/parse.py
pypykko/reinflect.py
pypykko/scriptutils.py
pypykko/tokenizer.py
pypykko/utils.py
pypykko/scripts/__init__.py
pypykko/scripts/constants.py
pypykko/scripts/file_tools.py
pypykko/tools/__init__.py
pypykko/tools/generate.py
pypykko/tools/normalize.py
pypykko/tools/parse.py
pypykko/tools/tokenizer.py
pypykko/tools/utils.py
pypykko-0.3.0.dist-info/licenses/LICENSE
pypykko-0.3.0.dist-info/METADATA
pypykko-0.3.0.dist-info/WHEEL
pypykko-0.3.0.dist-info/top_level.txt
pypykko-0.3.0.dist-info/RECORD
