Metadata-Version: 2.4
Name: pypykko
Version: 0.3.0
Summary: A pure-python wrapper for the pykko Finnish morphological analyser and inflector
Home-page: https://github.com/fergusq/fst-python
Author: Théo Salmenkivi-Friberg
Author-email: theo.friberg@helsinki.f
License: MIT
Project-URL: Bug Tracker, https://github.com/fergusq/fst-python/issues
Keywords: finnish nlp morphology
Classifier: License :: OSI Approved :: GNU General Public License v3 or later (GPLv3+)
Classifier: Programming Language :: Python
Classifier: Programming Language :: Python :: 3
Requires-Python: >=3.8
License-File: LICENSE
Requires-Dist: kfst>=4.3.3-beta
Dynamic: license-file
